EthIefLab/Experiment.py
EthIefLab/ExperimentHandler.py
EthIefLab/KillableThread.py
EthIefLab/ObservableList.py
EthIefLab/__init__.py
EthIefLab/Controls/ControlPanel.py
EthIefLab/Controls/CustomFrame.py
EthIefLab/Controls/CustomTable.py
EthIefLab/Controls/DeviceSelector.py
EthIefLab/Controls/ParameterTable.py
EthIefLab/Controls/PlotControl.py
EthIefLab/Controls/__init__.py
EthIefLab-1.0.0.dist-info/LICENSE.txt
EthIefLab-1.0.0.dist-info/METADATA
EthIefLab-1.0.0.dist-info/WHEEL
EthIefLab-1.0.0.dist-info/entry_points.txt
EthIefLab-1.0.0.dist-info/top_level.txt
EthIefLab-1.0.0.dist-info/RECORD
