Metadata-Version: 2.1
Name: EthIefLab
Version: 1.0.0
Summary: Library for UI used in lab experiments
Home-page: https://github.com/dowerner/ETH_IEF_LAB_python_lab_tools
Author: Dominik Werner
Author-email: dominikw@bluewin.ch
License: UNKNOWN
Keywords: science software development
Platform: UNKNOWN
Classifier: Development Status :: 3 - Alpha
Classifier: Programming Language :: Python :: 3
Classifier: Programming Language :: Python :: 3.4
Classifier: Programming Language :: Python :: 3.5
Classifier: Programming Language :: Python :: 3.6
Classifier: Programming Language :: Python :: 3.7
Requires-Dist: numpy
Requires-Dist: matplotlib
